github_blogging-0.1.1.dist-info/DESCRIPTION.rst
github_blogging-0.1.1.dist-info/METADATA
github_blogging-0.1.1.dist-info/RECORD
github_blogging-0.1.1.dist-info/WHEEL
github_blogging-0.1.1.dist-info/entry_points.txt
github_blogging-0.1.1.dist-info/metadata.json
github_blogging-0.1.1.dist-info/top_level.txt
src/__init__.py
src/blogging.py
